labo/__init__.py
labo/config.py
labo/main.py
labo/template.py
labo-0.1.4.dist-info/LICENSE
labo-0.1.4.dist-info/METADATA
labo-0.1.4.dist-info/WHEEL
labo-0.1.4.dist-info/entry_points.txt
labo-0.1.4.dist-info/top_level.txt
labo-0.1.4.dist-info/RECORD
